{"name":"Navigate to a different screen","id":"navigation;navigate-to-a-different-screen","testSteps":[{"number":1,"description":"Given I am on the welcome screen","duration":7489,"startTime":"2021-02-05T22:21:09.694852-08:00[America/Los_Angeles]","screenshots":[{"screenshot":"85c08a5591903c362d343ec38e52f65b2e2865e73eabb023a0190e6d2d74eb9f.png","timeStamp":1612592477183}],"result":"SUCCESS","precondition":false,"level":0,"children":[{"number":2,"description":"Click login","duration":1377,"startTime":"2021-02-05T22:21:15.799996-08:00[America/Los_Angeles]","screenshots":[{"screenshot":"f40d64dddbbe61a85da1a107a615d3dfe5048524e3974ac606c6c0136f49a19f.png","timeStamp":1612592476428},{"screenshot":"85c08a5591903c362d343ec38e52f65b2e2865e73eabb023a0190e6d2d74eb9f.png","timeStamp":1612592477177}],"result":"SUCCESS","precondition":false,"level":1}]},{"number":3,"description":"And I enter the correct username","duration":1288,"startTime":"2021-02-05T22:21:17.184603-08:00[America/Los_Angeles]","screenshots":[{"screenshot":"51641ae217e528d4210c6caba811318af7e83f0acc99ad8575945096751c9f2a.png","timeStamp":1612592478472}],"result":"SUCCESS","precondition":false,"level":0,"children":[{"number":4,"description":"Fill out username: john@mailinator.com","duration":1274,"startTime":"2021-02-05T22:21:17.191615-08:00[America/Los_Angeles]","screenshots":[{"screenshot":"51641ae217e528d4210c6caba811318af7e83f0acc99ad8575945096751c9f2a.png","timeStamp":1612592478466}],"result":"SUCCESS","precondition":false,"level":1}]},{"number":5,"description":"And I enter a valid password","duration":1166,"startTime":"2021-02-05T22:21:18.473376-08:00[America/Los_Angeles]","screenshots":[{"screenshot":"f4fae11543cfc1ee81370678c9820a2e2994f6704f082a84439d319618f8c722.png","timeStamp":1612592479639}],"result":"SUCCESS","precondition":false,"level":0,"children":[{"number":6,"description":"Fill out password: 12345#","duration":1153,"startTime":"2021-02-05T22:21:18.480615-08:00[America/Los_Angeles]","screenshots":[{"screenshot":"f4fae11543cfc1ee81370678c9820a2e2994f6704f082a84439d319618f8c722.png","timeStamp":1612592479634}],"result":"SUCCESS","precondition":false,"level":1}]},{"number":7,"description":"Then I should be taken to the Welcome Screen","duration":2397,"startTime":"2021-02-05T22:21:19.640076-08:00[America/Los_Angeles]","screenshots":[{"screenshot":"8f3e66d2b6495e1886b3d2b2cd9847e2c97ff18d9d7f857d56d19fa8857c1080.png","timeStamp":1612592482037}],"result":"SUCCESS","precondition":false,"level":0},{"number":8,"description":"When I click on the notifications button","duration":503,"startTime":"2021-02-05T22:21:22.039121-08:00[America/Los_Angeles]","screenshots":[{"screenshot":"7afab6b150c82bb531d807ce80580d873aa66457353376fd63d50f6632283616.png","timeStamp":1612592482543}],"result":"SUCCESS","precondition":false,"level":0},{"number":9,"description":"Then I should end up on a new screen","duration":740,"startTime":"2021-02-05T22:21:22.543990-08:00[America/Los_Angeles]","screenshots":[{"screenshot":"7884a4758575395ae1fd3dbc0766c1e76b6a9a3811fbf1adda45df9d99a075ab.png","timeStamp":1612592483284}],"result":"SUCCESS","precondition":false,"level":0,"children":[{"number":10,"description":"Notification fragment exists","duration":660,"startTime":"2021-02-05T22:21:22.615898-08:00[America/Los_Angeles]","screenshots":[{"screenshot":"549fa4d1da5df8b8133dc3aa6bae4dec6d5107c682d25bfb427e6629398d1281.png","timeStamp":1612592482892},{"screenshot":"7884a4758575395ae1fd3dbc0766c1e76b6a9a3811fbf1adda45df9d99a075ab.png","timeStamp":1612592483276}],"result":"SUCCESS","precondition":false,"level":1}]}],"userStory":{"id":"navigation","storyName":"Navigation","path":"Navigation.feature","type":"feature"},"featureTag":{"name":"Navigation","type":"feature","displayName":"Navigation"},"title":"Navigate to a different screen","tags":[{"name":"navigation","type":"tag","displayName":"navigation"},{"name":"android","type":"tag","displayName":"android"},{"name":"Navigation","type":"feature","displayName":"Navigation"}],"startTime":"2021-02-05T22:21:09.690366-08:00[America/Los_Angeles]","duration":13594,"projectKey":"","sessionId":"b183fa17-3d0d-4604-ae24-fff90228a68f","driver":"appium","isManualTestingUpToDate":false,"manual":false,"testSource":"Cucumber","result":"SUCCESS"}